core/Youtube.py
core/__init__.py
dataclasses/YoutubeResponse.py
dataclasses/__init__.py
dataclasses/format_classification.py
dataclasses/formats/AudioFormat.py
dataclasses/formats/MediaFormat.py
dataclasses/formats/VideoFormat.py
dataclasses/formats/__init__.py
mixins/SerializableMixin.py
mixins/__init__.py
tubegrab-0.0.0.dist-info/licenses/LICENSE
types/__init__.py
utils/ClassifyFormat.py
utils/__init__.py
utils/extract_youtube_id.py
utils/transform_ytdlp_response.py
utils/format_classifier/__init__.py
utils/format_classifier/classify_audio_format.py
utils/format_classifier/classify_video_format.py
tubegrab-0.0.0.dist-info/METADATA
tubegrab-0.0.0.dist-info/WHEEL
tubegrab-0.0.0.dist-info/top_level.txt
tubegrab-0.0.0.dist-info/RECORD
