Metadata-Version: 2.4
Name: tubegrab
Version: 0.0.0
Summary: A simple library for extracting YouTube content using yt-dlp
Author-email: Sachin Acharya <tubegrab.sachin.acharya@gmail.com>
Project-URL: Homepage, https://github.com/sachin-acharya-projects/youtube-extractor
Project-URL: Issues, https://github.com/sachin-acharya-projects/youtube-extractor/issues
Keywords: youtube,extract,yt-dlp
Classifier: Programming Language :: Python :: 3
Classifier: Operating System :: OS Independent
Classifier: Topic :: Multimedia :: Video
Requires-Python: >=3.11
License-File: LICENSE
Requires-Dist: yt-dlp>=2024.7.7
Provides-Extra: dev
Dynamic: license-file
